spacepacket/__init__.py
spacepacket/constants.py
spacepacket/core.py
spacepacket/transport/__init__.py
spacepacket/transport/base.py
spacepacket/transport/udp.py
spacepacket-2.0.0.dist-info/LICENSE.txt
spacepacket-2.0.0.dist-info/METADATA
spacepacket-2.0.0.dist-info/WHEEL
spacepacket-2.0.0.dist-info/top_level.txt
spacepacket-2.0.0.dist-info/RECORD
