Metadata-Version: 2.1
Name: spacepacket
Version: 2.0.0
Summary: CCSDS Space Packet Protocol
Author-email: LibreCube <info@librecube.org>
License: MIT
License-File: LICENSE.txt
